config.py
data_handler.py
gpt_client.py
model_builder.py
model_builder_client.py
optimizer.py
password_utils.py
portfolio_backtest.py
position_manager.py
safe_html_parser.py
server.py
simulation.py
strategy_optimizer.py
trade_manager.py
trading_bot.py
utils.py
services/__init__.py
services/data_handler_service.py
services/model_builder_service.py
services/trade_manager_service.py
trading_bot_x-0.1.1.dist-info/licenses/LICENSE
trading_bot_x-0.1.1.dist-info/METADATA
trading_bot_x-0.1.1.dist-info/WHEEL
trading_bot_x-0.1.1.dist-info/top_level.txt
trading_bot_x-0.1.1.dist-info/RECORD
