Metadata-Version: 2.4
Name: trading-bot-x
Version: 0.1.1
Summary: Пример торгового бота на Python.
Author: Project Authors
License-Expression: MIT
License-File: LICENSE
Requires-Dist: flask>=3.0.2
Dynamic: license-file
